compressa/perf/__init__.py
compressa/perf/cli/__init__.py
compressa/perf/cli/__main__.py
compressa/perf/cli/pdf_tools.py
compressa/perf/cli/tools.py
compressa/perf/data/models.py
compressa/perf/db/__init__.py
compressa/perf/db/__main__.py
compressa/perf/db/db_inserts.py
compressa/perf/db/operations.py
compressa/perf/db/setup.py
compressa/perf/db/writer.py
compressa/perf/experiment/analysis.py
compressa/perf/experiment/config.py
compressa/perf/experiment/continuous_stress.py
compressa/perf/experiment/inference.py
compressa/utils.py
compressa_perf-0.2.6.dist-info/LICENSE
compressa_perf-0.2.6.dist-info/METADATA
compressa_perf-0.2.6.dist-info/WHEEL
compressa_perf-0.2.6.dist-info/entry_points.txt
compressa_perf-0.2.6.dist-info/RECORD
